[
  {
    "address": "http://15wyktxzla.dianshe.top/live/cx_369866.flv",
    "img": "https://jhgohgfhgfh01.biexd.xyz/7701/live/images/b7092fb325e6f16dff45c6f13670872d",
    "title": "粉嫩葡萄"
  },
  {
    "address": "rtmp://vips.mpsjk.xyz/live/20736_1754228012",
    "img": "http://bgt.beifs.xyz/upload//thumb/20250803/08075720121034038.png",
    "title": "澳门现场博彩"
  },
  {
    "address": "http://laowafeb08.sturl.top/live/cx_382518.flv",
    "img": "https://jhgohgfhgfh01.biexd.xyz/7701/live/images/8607aa70a2c2a181983b6b1dce1d59ab",
    "title": "大头菜"
  },
  {
    "address": "rtmp://xueli130.vihyvz.top/live/4652_1754618",
    "img": "http://xuelii.tuise.top/images/b62702b8d2a6979602.jpg",
    "title": "雪梨味汽水儿"
  },
  {
    "address": "rtmp://xueli130.vihyvz.top/live/4821_1754602",
    "img": "http://xuelii.tuise.top/imgqq/919e4b089d65b555ee.jpg",
    "title": "玲娜贝儿"
  },
  {
    "address": "rtmp://mg0oa.mbubmxok.top/live/5328_1754735",
    "img": "http://mgysals.xavwem.top/imgmg/f6a2374e5e620cf6e8.jpg",
    "title": "小南瓜"
  },
  {
    "address": "rtmp://mg0oa.mbubmxok.top/live/5614_1754883",
    "img": "http://mgysals.xavwem.top/imgmg/17fe4267f84bd3da9c.jpg",
    "title": "小橙橙"
  },
  {
    "address": "rtmp://mg0oa.mbubmxok.top/live/5581_1754595",
    "img": "http://mgysals.xavwem.top/imgmg/365340e20784f2dd58.jpg",
    "title": "性感幺妹"
  },
  {
    "address": "rtmp://mg0oa.mbubmxok.top/live/5088_1754387",
    "img": "http://mgysals.xavwem.top/imgmg/3c7d85c619febf40aa.jpg",
    "title": "小海绵."
  },
  {
    "address": "http://laowafeb08.sturl.top/live/cx_360139.flv",
    "img": "https://jhgohgfhgfh01.biexd.xyz/7701/live/images/503d24c887471d40f70b33db17bb16cf",
    "title": "奶茶好甜"
  },
  {
    "address": "rtmp://mg0oa.mbubmxok.top/live/5300_1754168",
    "img": "http://mgysals.xavwem.top/imgmg/6d2e7e7d15286efbf3.jpg",
    "title": "小蘭心"
  },
  {
    "address": "rtmp://mg0oa.mbubmxok.top/live/5406_1754367",
    "img": "http://mgysals.xavwem.top/imgmg/4e4307e3ce01a5be9c.jpg",
    "title": "当午w"
  },
  {
    "address": "rtmp://mg0oa.mbubmxok.top/live/5176_1754124",
    "img": "http://mgysals.xavwem.top/imgmg/54a02ffe9ea61d2815.jpg",
    "title": "你的丫头吖"
  },
  {
    "address": "rtmp://mg0oa.mbubmxok.top/live/5597_1754463",
    "img": "http://mgysals.xavwem.top/imgmg/13455546827d052e84.jpg",
    "title": "性感十一"
  },
  {
    "address": "rtmp://mg0oa.mbubmxok.top/live/5787_1754831",
    "img": "http://mgysals.xavwem.top/imgmg/be3f53fd3c4b2d82d9.jpg",
    "title": "小尤莉"
  },
  {
    "address": "rtmp://mg0oa.mbubmxok.top/live/5221_1754139",
    "img": "http://mgysals.xavwem.top/imgmg/84836408314be16258.jpg",
    "title": "妖姬不是妖"
  },
  {
    "address": "rtmp://mg0oa.mbubmxok.top/live/5878_1754297",
    "img": "http://mgysals.xavwem.top/imgmg/2b1e4236f3ab3d1147.jpg",
    "title": "叉叉"
  },
  {
    "address": "rtmp://mg0oa.mbubmxok.top/live/5264_1754154",
    "img": "http://mgysals.xavwem.top/imgmg/4f45fad294073f1af6.jpg",
    "title": "小女孩"
  },
  {
    "address": "rtmp://mg0oa.mbubmxok.top/live/5135_1754785",
    "img": "http://mgysals.xavwem.top/imgmg/2ac3a8f59df794c5cb.jpg",
    "title": "大奶心"
  },
  {
    "address": "rtmp://mg0oa.mbubmxok.top/live/5581_1754504",
    "img": "http://mgysals.xavwem.top/imgmg/47f8119f0e5c69d68b.jpg",
    "title": "子乔"
  },
  {
    "address": "rtmp://mg0oa.mbubmxok.top/live/5782_1754483",
    "img": "http://mgysals.xavwem.top/imgmg/d3ed68283c7b989c85.jpg",
    "title": "喜宝"
  },
  {
    "address": "rtmp://mg0oa.mbubmxok.top/live/5459_1754699",
    "img": "http://mgysals.xavwem.top/imgmg/0458a2856ef930cf1f.jpg",
    "title": "小包包"
  },
  {
    "address": "rtmp://mg0oa.mbubmxok.top/live/5766_1754541",
    "img": "http://mgysals.xavwem.top/imgmg/a5a04e9b2585b3d0cb.jpg",
    "title": "冰露"
  },
  {
    "address": "rtmp://mg0oa.mbubmxok.top/live/5961_1754584",
    "img": "http://mgysals.xavwem.top/imgmg/dfd6a27f8c471c4f5b.jpg",
    "title": "你的小湿妹"
  },
  {
    "address": "rtmp://xinfusz.zzlsnp.top/live/6376_1754788",
    "img": "http://xingr.biognax.xyz/imgxr/b3fc534e6537a50820.jpg",
    "title": "嫩模呢"
  }
]