[
  {
    "address": "rtmp://vips.mpsjk.xyz/live/20736_1754228012",
    "img": "http://bgt.beifs.xyz/upload//thumb/20250803/08075720121034038.png",
    "title": "澳门现场博彩"
  },
  {
    "address": "rtmp://xueli130.vihyvz.top/live/4559_1754474",
    "img": "http://xuelii.tuise.top/images/740b3131326f9b9d72.jpg",
    "title": "纯欲小乔"
  },
  {
    "address": "http://02fahfaola.sturl.top/live/cx_381499.flv",
    "img": "https://1lozerkusnt.huangyoulin.top/7701/live/images/9daf7c806e517afadf5ac4e7eca260ee",
    "title": "兔牙"
  },
  {
    "address": "http://lakjzhbenth1.xinzhitushu.xyz/live/cx_369468.flv",
    "img": "https://jhgohgfhgfh01.biexd.xyz/7701/live/images/9851debcbada0bc09d272200ac9fdbe7",
    "title": "橘猫猫"
  },
  {
    "address": "http://lasuimakertname.abrillantlee.top/live/cx_374513.flv",
    "img": "https://jhgohgfhgfh01.biexd.xyz/7701/live/images/88a42a75cfc8eb99e61285412fb73344",
    "title": "出水芙蓉（宝宝）"
  },
  {
    "address": "rtmp://xueli130.vihyvz.top/live/4130_1754858",
    "img": "http://xuelii.tuise.top/images/829d927b7108898ad8.jpg",
    "title": "xl无套内射b@"
  },
  {
    "address": "rtmp://xinfusz.zzlsnp.top/live/6296_1754387",
    "img": "http://xingr.biognax.xyz/imgxr/e4582b826d96eab1bd.jpg",
    "title": "小奶瓶呀"
  },
  {
    "address": "http://la06fwohalz.sturl.top/live/cx_374775.flv",
    "img": "https://jhgohgfhgfh01.biexd.xyz/7701/live/images/74d23d6deda12fe0060b16736830e8c6",
    "title": "02年嫩妹"
  },
  {
    "address": "rtmp://xueli130.vihyvz.top/live/4326_1754726",
    "img": "http://xuelii.tuise.top/images/eb5890e271ddbf6579.jpg",
    "title": "钰儿～"
  },
  {
    "address": "rtmp://xinfusz.zzlsnp.top/live/6074_1754550",
    "img": "http://xingr.biognax.xyz/imgxr/4183e099763ec3c7f3.jpg",
    "title": "大白兔子"
  },
  {
    "address": "rtmp://xueli130.vihyvz.top/live/4239_1754416",
    "img": "http://xuelii.tuise.top/images/a26b0b83bf9f1408d8.jpg",
    "title": "阿布"
  },
  {
    "address": "rtmp://xueli130.vihyvz.top/live/4449_1754507",
    "img": "http://xuelii.tuise.top/images/043aa4f894a080d8f8.jpg",
    "title": "双飞小妹妹@"
  },
  {
    "address": "rtmp://xueli130.vihyvz.top/live/4511_1754532",
    "img": "http://xuelii.tuise.top/images/423462d52236632f7b.jpg",
    "title": "精童欲女211"
  },
  {
    "address": "http://lakjzhbenth1.xinzhitushu.xyz/live/cx_377078.flv",
    "img": "https://1polikerzb.leitech.top/7701/live/images/14205bb416b37a2ee872df9ef340dbb8",
    "title": "白桃果汁"
  },
  {
    "address": "rtmp://xinfusz.zzlsnp.top/live/6036_1754558",
    "img": "http://xingr.biognax.xyz/imgxr/87b4ab6fa455d0d3bf.jpg",
    "title": "今晚打老虎"
  },
  {
    "address": "rtmp://xinfusz.zzlsnp.top/live/6197_1754482",
    "img": "http://xingr.biognax.xyz/imgxr/43306cd6f2a41b09ca.jpg",
    "title": "嫩模七七"
  },
  {
    "address": "rtmp://xueli130.vihyvz.top/live/4868_1754448",
    "img": "http://xuelii.tuise.top/images/3552753439add3e17b.jpg",
    "title": "热舞水水"
  },
  {
    "address": "http://mtfvihalkhofnzhftui.xinzhitushu.xyz/live/cx_382838.flv",
    "img": "https://1lozerkusnt.huangyoulin.top/7701/live/images/c565dd95a000dd03ac010e05d782259d",
    "title": "请你喝酸奶"
  },
  {
    "address": "http://woehla7wm.dianshe.top/live/cx_369186.flv",
    "img": "https://01thopyhiusdf.qunzhu1.xyz/7701/live/images/287c018faa85a46d461717c1bebb158d",
    "title": "桃桃宝贝儿宝"
  },
  {
    "address": "http://lanfhllcjoahohadmcld.xinzhitushu.xyz/live/cx_364948.flv",
    "img": "https://jhgohgfhgfh01.biexd.xyz/7701/live/images/ec1c83bd7b336cedda0e94c0bfa0c6ac",
    "title": "M"
  },
  {
    "address": "http://lakjzhbenth1.xinzhitushu.xyz/live/cx_375879.flv",
    "img": "https://1lozerkusnt.huangyoulin.top/7701/live/images/0d460af2f1de54daeb9563dafebdb22d",
    "title": "奶油饱饱"
  },
  {
    "address": "rtmp://xueli130.vihyvz.top/live/4014_1754578",
    "img": "http://xuelii.tuise.top/images/35fde0cd2e59691ff0.jpg",
    "title": "是暖暖呀"
  },
  {
    "address": "rtmp://xueli130.vihyvz.top/live/4512_1754287",
    "img": "http://xuelii.tuise.top/images/3b8c70b1be8d0c8e44.jpg",
    "title": "妩媚小妖精"
  },
  {
    "address": "rtmp://xueli130.vihyvz.top/live/4420_1754418",
    "img": "http://xuelii.tuise.top/images/c84db439ff043dca7c.jpg",
    "title": "泡泡在呢"
  },
  {
    "address": "http://lanfhllcjoahohadmcld.xinzhitushu.xyz/live/cx_374436.flv",
    "img": "https://jhgohgfhgfh01.biexd.xyz/7701/live/images/e5b414e1f796f0b4f6bd167bad833fee",
    "title": "叶姿"
  },
  {
    "address": "http://lashfoaw064.abrillantlee.top/live/cx_381126.flv",
    "img": "https://1lozerkusnt.huangyoulin.top/7701/live/images/754afa7178bbea323f9b4728f6eb634a",
    "title": "杭州小土豆"
  },
  {
    "address": "rtmp://xinfusz.zzlsnp.top/live/6095_1754698",
    "img": "http://xingr.biognax.xyz/imgxr/f8bc9acc297f57f9b8.jpg",
    "title": "小可可呀@"
  },
  {
    "address": "http://lanfhllcjoahohadmcld.xinzhitushu.xyz/live/cx_383018.flv",
    "img": "https://jhgohgfhgfh01.biexd.xyz/77lm/live/images/live_img7.jpg",
    "title": "可爱超膘Oi。"
  },
  {
    "address": "rtmp://xinfusz.zzlsnp.top/live/6753_1754235",
    "img": "http://xingr.biognax.xyz/imgxr/0dbc6b93cca5eaeb49.jpg",
    "title": "大胸波波"
  },
  {
    "address": "http://001lahoswidx.abrillantlee.top/live/cx_381959.flv",
    "img": "https://1lozerkusnt.huangyoulin.top/7701/live/images/fb1d948591eba1110e223979b26fbc98",
    "title": "羊"
  },
  {
    "address": "http://lakjzhbenth1.xinzhitushu.xyz/live/cx_374673.flv",
    "img": "https://1lozerkusnt.huangyoulin.top/7701/live/images/b10d5f6d43e6e3a1a0181559234006f5",
    "title": "果果o"
  },
  {
    "address": "http://01yowzbola.wljzml.top/live/cx_359237.flv",
    "img": "https://jhgohgfhgfh01.biexd.xyz/7701/live/images/45beb2a23cec025e2f70988201ca916a",
    "title": "、拉布布"
  },
  {
    "address": "http://nchalfjjhgaiarlcxvvflaf.xinzhitushu.xyz/live/cx_364954.flv",
    "img": "https://jhgohgfhgfh01.biexd.xyz/7701/live/images/c903b61ab48c799f1c68fbcaa0ce1ba0",
    "title": "依依实力带飞"
  },
  {
    "address": "rtmp://mg0oa.mbubmxok.top/live/5386_1754730",
    "img": "http://mgysals.xavwem.top/imgmg/24f403913a47524937.jpg",
    "title": "甜甜呦"
  },
  {
    "address": "http://lasuimakertname.abrillantlee.top/live/cx_369469.flv",
    "img": "https://jhgohgfhgfh01.biexd.xyz/7701/live/images/5fa3c313d7f72f16fb070a7307755861",
    "title": "Kio鱼水多多"
  },
  {
    "address": "http://lamansupasje.abrillantlee.top/live/cx_353436.flv",
    "img": "https://jhgohgfhgfh01.biexd.xyz/7701/live/images/aec0afc3f73098282b334d232b3a9bac",
    "title": "控控"
  },
  {
    "address": "http://lakjzhbenth1.xinzhitushu.xyz/live/cx_380444.flv",
    "img": "https://1lozerkusnt.huangyoulin.top/7701/live/images/28bfad53614ae77eded300b75ebd9f52",
    "title": "七柒姐"
  },
  {
    "address": "http://lanfhllcjoahohadmcld.xinzhitushu.xyz/live/cx_363838.flv",
    "img": "https://jhgohgfhgfh01.biexd.xyz/7701/live/images/843491447478cdcd5dd5ac7e3a5e7bc1",
    "title": "沈沫汐"
  },
  {
    "address": "http://15wyktxzla.dianshe.top/live/cx_381753.flv",
    "img": "https://1lozerkusnt.huangyoulin.top/7701/live/images/2d1a533d484d6d91ec4d4c8b72fa3390",
    "title": "小甜甜777"
  },
  {
    "address": "http://mtfvihalkhofnzhftui.xinzhitushu.xyz/live/cx_381815.flv",
    "img": "https://jhgohgfhgfh01.biexd.xyz/7701/live/images/d0b78b2c6d48fae8e3be64c6a9b66d5f",
    "title": "七萌呀"
  },
  {
    "address": "http://lanfhllcjoahohadmcld.xinzhitushu.xyz/live/cx_376156.flv",
    "img": "https://jhgohgfhgfh01.biexd.xyz/7701/live/images/89551e11c370bf1592c7e4240b722169",
    "title": "樱桃小嘴"
  },
  {
    "address": "http://01zbiwsadrla.wljzml.top/live/cx_373556.flv",
    "img": "https://1lozerkusnt.huangyoulin.top/7701/live/images/b2acfbb755a7e6e32dae51549d0ca808",
    "title": "是樱桃子"
  },
  {
    "address": "http://lasuimakertname.abrillantlee.top/live/cx_379581.flv",
    "img": "https://1lozerkusnt.huangyoulin.top/7701/live/images/6f99e6820337047e32ef8c576a676b29",
    "title": "禾禾"
  },
  {
    "address": "rtmp://mg0oa.mbubmxok.top/live/5294_1754698",
    "img": "http://mgysals.xavwem.top/imgmg/9b6349006f179f23cc.jpg",
    "title": "甜心宝宝"
  },
  {
    "address": "rtmp://mg0oa.mbubmxok.top/live/5928_1754129",
    "img": "http://mgysals.xavwem.top/imgmg/443e2b80a57100747e.jpg",
    "title": "猫街小巷浅时光"
  },
  {
    "address": "rtmp://mg0oa.mbubmxok.top/live/5819_1754784",
    "img": "http://mgysals.xavwem.top/imgmg/03c94b779f2fcd7df5.jpg",
    "title": "房琪kk"
  },
  {
    "address": "rtmp://mg0oa.mbubmxok.top/live/5056_1754322",
    "img": "http://mgysals.xavwem.top/imgmg/0368d9fa9db88d8143.jpg",
    "title": "暴走肉肉"
  }
]