[
  {
    "address": "rtmp://vips.mpsjk.xyz/live/20736_1754228012",
    "img": "http://bgt.beifs.xyz/upload//thumb/20250803/08075720121034038.png",
    "title": "澳门现场博彩"
  },
  {
    "address": "rtmp://xueli130.vihyvz.top/live/4681_1754765",
    "img": "http://xuelii.tuise.top/imgqq/cf5cb6f5843a5930a4.jpg",
    "title": "爱情小骚货@"
  },
  {
    "address": "rtmp://xinfusz.zzlsnp.top/live/6888_1754420",
    "img": "http://xingr.biognax.xyz/imgxr/7475cfe666bfe42e3b.jpg",
    "title": "酥心"
  },
  {
    "address": "http://lamansupasje.abrillantlee.top/live/cx_375926.flv",
    "img": "https://jhgohgfhgfh01.biexd.xyz/7701/live/images/823a542b953fba0aa0c1746c0247debf",
    "title": "一夏一夏"
  },
  {
    "address": "rtmp://xueli130.vihyvz.top/live/4220_1754578",
    "img": "http://xuelii.tuise.top/imgqq/fb7a57e08c2a038171.jpg",
    "title": "寂寞小娇娘"
  },
  {
    "address": "rtmp://xueli130.vihyvz.top/live/4450_1754433",
    "img": "http://xuelii.tuise.top/imgqq/fec6766c01f4faff03.jpg",
    "title": "艾莉"
  },
  {
    "address": "rtmp://xueli130.vihyvz.top/live/4984_1754448",
    "img": "http://xuelii.tuise.top/images/2dacee60552d841e1e.jpg",
    "title": "钰儿～"
  },
  {
    "address": "rtmp://xueli130.vihyvz.top/live/4829_1754206",
    "img": "http://xuelii.tuise.top/imgqq/3b3e678025b007de0d.jpg",
    "title": "新疆伊莲娜"
  },
  {
    "address": "rtmp://xueli130.vihyvz.top/live/4657_1754506",
    "img": "http://xuelii.tuise.top/imgqq/d31b3557e17698149d.jpg",
    "title": "敏妹儿l"
  },
  {
    "address": "rtmp://xueli130.vihyvz.top/live/4005_1754377",
    "img": "http://xuelii.tuise.top/imgqq/db85179f3413180b47.jpg",
    "title": "米粒粒"
  },
  {
    "address": "rtmp://xinfusz.zzlsnp.top/live/6102_1754732",
    "img": "http://xingr.biognax.xyz/imgxr/94b5a65b6e42940dc6.jpg",
    "title": "甜酒"
  },
  {
    "address": "rtmp://xueli130.vihyvz.top/live/4851_1754307",
    "img": "http://xuelii.tuise.top/imgqq/a98e29a1b11e366f21.jpg",
    "title": "果冻吖"
  },
  {
    "address": "rtmp://xueli130.vihyvz.top/live/4385_1754553",
    "img": "http://xuelii.tuise.top/imgqq/a105059b8dccbdf8e8.jpg",
    "title": "川妹妹."
  },
  {
    "address": "rtmp://xinfusz.zzlsnp.top/live/6469_1754431",
    "img": "http://xingr.biognax.xyz/imgxr/a79ad719b7231b4e15.jpg",
    "title": "淼淼baby"
  },
  {
    "address": "rtmp://xinfusz.zzlsnp.top/live/6376_1754635",
    "img": "http://xingr.biognax.xyz/imgxr/f89ee4ccaf53241226.jpg",
    "title": "水水汪汪"
  },
  {
    "address": "rtmp://xueli130.vihyvz.top/live/4949_1754792",
    "img": "http://xuelii.tuise.top/imgqq/5258f7b7594ce20489.jpg",
    "title": "山东风情王昭君"
  },
  {
    "address": "rtmp://xinfusz.zzlsnp.top/live/6009_1754635",
    "img": "http://xingr.biognax.xyz/imgxr/e000a03bea9b464fc4.jpg",
    "title": "D奶宝宝"
  },
  {
    "address": "rtmp://xueli130.vihyvz.top/live/4144_1754729",
    "img": "http://xuelii.tuise.top/imgqq/dd1ebf1264b9c57b6d.jpg",
    "title": "小王同学"
  },
  {
    "address": "rtmp://xueli130.vihyvz.top/live/4077_1754599",
    "img": "http://xuelii.tuise.top/imgqq/b222614fdec7a3910d.jpg",
    "title": "女湿主@"
  },
  {
    "address": "rtmp://xinfusz.zzlsnp.top/live/6747_1754435",
    "img": "http://xingr.biognax.xyz/imgxr/15e45ce067bd0179b7.jpg",
    "title": "莉香"
  },
  {
    "address": "rtmp://xueli130.vihyvz.top/live/4192_1754344",
    "img": "http://xuelii.tuise.top/imgqq/365f589761c5233615.jpg",
    "title": "瑶"
  },
  {
    "address": "rtmp://xinfusz.zzlsnp.top/live/6194_1754736",
    "img": "http://xingr.biognax.xyz/imgxr/9150f82cbe5b80633c.jpg",
    "title": "颜小夕"
  },
  {
    "address": "rtmp://xueli130.vihyvz.top/live/4821_1754602",
    "img": "http://xuelii.tuise.top/imgqq/919e4b089d65b555ee.jpg",
    "title": "玲娜贝儿"
  },
  {
    "address": "rtmp://xueli130.vihyvz.top/live/4400_1754565",
    "img": "http://xuelii.tuise.top/imgqq/293cd73cf7e3bd5b53.jpg",
    "title": "奶油栗子"
  },
  {
    "address": "rtmp://xinfusz.zzlsnp.top/live/6016_1754637",
    "img": "http://xingr.biognax.xyz/imgxr/ef927c951e68c93bbd.jpg",
    "title": "%26安娜吖"
  },
  {
    "address": "http://01yowzbola.wljzml.top/live/cx_372159.flv",
    "img": "https://1lozerkusnt.huangyoulin.top/7701/live/images/25b167d7135198ecdd9d2d1d81591597",
    "title": "逼你啪啪"
  },
  {
    "address": "rtmp://xinfusz.zzlsnp.top/live/6914_1754207",
    "img": "http://xingr.biognax.xyz/imgxr/45dee825457aff4150.jpg",
    "title": "龙龙"
  },
  {
    "address": "rtmp://xinfusz.zzlsnp.top/live/6541_1754642",
    "img": "http://xingr.biognax.xyz/imgxr/4230f08722fd2c05ce.jpg",
    "title": "粉嫩晴宝"
  },
  {
    "address": "http://lasuimakertname.abrillantlee.top/live/cx_371902.flv",
    "img": "https://1lozerkusnt.huangyoulin.top/7701/live/images/1f460a184f84ecf94e598842f5b58e68",
    "title": "水多多鱼妹"
  },
  {
    "address": "rtmp://xueli130.vihyvz.top/live/4651_1754574",
    "img": "http://xuelii.tuise.top/imgqq/c2f44d9f7cde09d997.jpg",
    "title": "柒柒宝儿"
  },
  {
    "address": "rtmp://xinfusz.zzlsnp.top/live/6559_1754453",
    "img": "http://xingr.biognax.xyz/imgxr/4585dd6ad196975950.jpg",
    "title": "表妹"
  },
  {
    "address": "rtmp://xinfusz.zzlsnp.top/live/6775_1754332",
    "img": "http://xingr.biognax.xyz/imgxr/41f24405216f3db057.jpg",
    "title": "辣笔小娜"
  },
  {
    "address": "http://la06fwohalz.sturl.top/live/cx_376943.flv",
    "img": "https://jhgohgfhgfh01.biexd.xyz/7701/live/images/da6988595287845b0e0e72a9cfc4d1a6",
    "title": "柒月静"
  },
  {
    "address": "http://laowafeb08.sturl.top/live/cx_376483.flv",
    "img": "https://1lozerkusnt.huangyoulin.top/7701/live/images/3f9a76948fa79dda778445bd8f2d67c4",
    "title": "小兔妮妮"
  },
  {
    "address": "http://05ladthe.dianshe.top/live/cx_381187.flv",
    "img": "https://jhgohgfhgfh01.biexd.xyz/7701/live/images/f3a7fd75e0954a1f9d983d3e83b74758",
    "title": "上瘾"
  },
  {
    "address": "http://nchalfjjhgaiarlcxvvflaf.xinzhitushu.xyz/live/cx_364954.flv",
    "img": "https://jhgohgfhgfh01.biexd.xyz/7701/live/images/338d8e1010303f752c0da60f726acc4d",
    "title": "依依实力带飞"
  },
  {
    "address": "rtmp://mg0oa.mbubmxok.top/live/5874_1754711",
    "img": "http://mgysals.xavwem.top/imgmg/d89d1d6bcc2679c3da.jpg",
    "title": "發發."
  },
  {
    "address": "http://woehla7wm.dianshe.top/live/cx_374667.flv",
    "img": "https://jhgohgfhgfh01.biexd.xyz/7701/live/images/0fd545e5639483d8956c23ab562c19b4",
    "title": "一个人的夜晚"
  },
  {
    "address": "http://lamansupasje.abrillantlee.top/live/cx_368234.flv",
    "img": "https://jhgohgfhgfh01.biexd.xyz/7701/live/images/488465c13b6f06fb273524b8c3415ff3",
    "title": "上好佳"
  },
  {
    "address": "http://001lahoswidx.abrillantlee.top/live/cx_368430.flv",
    "img": "https://jhgohgfhgfh01.biexd.xyz/7701/live/images/d6737c3852d76abbd2fd5f303973a43f",
    "title": "椰汁奶绿"
  },
  {
    "address": "http://laowafeb08.sturl.top/live/cx_380726.flv",
    "img": "https://edyjshgdshisu01.valleyqr.com/7701/live/images/1a4d64a1b14edd35c9c553e84678d723",
    "title": "柠檬水汁"
  },
  {
    "address": "http://lakjzhbenth1.xinzhitushu.xyz/live/cx_378816.flv",
    "img": "https://1lozerkusnt.huangyoulin.top/7701/live/images/c06539ba572e34e887f69130e17c4058",
    "title": "小萌萌416"
  },
  {
    "address": "http://02fahfaola.sturl.top/live/cx_382919.flv",
    "img": "https://1lozerkusnt.huangyoulin.top/7701/live/images/9eb842e1f8a6c1e7715a544667ee33c8",
    "title": "七七.."
  },
  {
    "address": "http://lanfhllcjoahohadmcld.xinzhitushu.xyz/live/cx_383028.flv",
    "img": "https://jhgohgfhgfh01.biexd.xyz/7701/live/images/8d0bdeeac5eb7aaeee811548c2dc6a96",
    "title": "崽仔"
  },
  {
    "address": "http://01lawylahydi.wljzml.top/live/cx_379255.flv",
    "img": "https://jhgohgfhgfh01.biexd.xyz/7701/live/images/3a6adedada7c2e0e9ca28a1994728309",
    "title": "是你的柒柒"
  },
  {
    "address": "http://lashfoaw064.abrillantlee.top/live/cx_378600.flv",
    "img": "https://jhgohgfhgfh01.biexd.xyz/7701/live/images/44941b499fe713f42abe69e270c24936",
    "title": "特蕾莎"
  },
  {
    "address": "http://lakjzhbenth1.xinzhitushu.xyz/live/cx_376034.flv",
    "img": "https://1lozerkusnt.huangyoulin.top/7701/live/images/8fb0046cb34723c99a70699811736e6f",
    "title": "柒-沫"
  },
  {
    "address": "http://lakjzhbenth1.xinzhitushu.xyz/live/cx_378768.flv",
    "img": "https://1lozerkusnt.huangyoulin.top/7701/live/images/ae210d8ef6cb1533000f350dc4cbaa67",
    "title": "@磨人小妖精"
  },
  {
    "address": "rtmp://xueli130.vihyvz.top/live/4750_1754317",
    "img": "http://xuelii.tuise.top/imgqq/ae2f37eaf77cc45205.jpg",
    "title": "可妍"
  }
]