[
  {
    "address": "rtmp://xinfusz.zzlsnp.top/live/6255_1754683",
    "img": "http://xingr.biognax.xyz/imgxr/1f8d3ecd0dfb3a4f89.jpg",
    "title": "你的皇后倩倩"
  },
  {
    "address": "rtmp://xueli130.vihyvz.top/live/4073_1754174",
    "img": "http://xuelii.tuise.top/images/7d52ee75fe5ce9f81e.jpg",
    "title": "阿布"
  },
  {
    "address": "rtmp://xinfusz.zzlsnp.top/live/6378_1754608",
    "img": "http://xingr.biognax.xyz/imgxr/516b9b3d032503c76e.jpg",
    "title": "库枫叶"
  },
  {
    "address": "rtmp://xinfusz.zzlsnp.top/live/6375_1754561",
    "img": "http://xingr.biognax.xyz/imgxr/2bd2b4e9fc90403afb.jpg",
    "title": "co酥酥"
  },
  {
    "address": "http://lamansupasje.abrillantlee.top/live/cx_366975.flv",
    "img": "https://jhgohgfhgfh01.biexd.xyz/7701/live/images/b08fbc44e2aead86547c875c3046d819",
    "title": "狂送高潮"
  },
  {
    "address": "http://02fahfaola.sturl.top/live/cx_376746.flv",
    "img": "https://1lozerkusnt.huangyoulin.top/7701/live/images/1bcaeb98167139527063e6979881b83e",
    "title": "泡芙奶心"
  },
  {
    "address": "rtmp://xueli130.vihyvz.top/live/4260_1754584",
    "img": "http://xuelii.tuise.top/images/8f75dfe70a59852c1b.jpg",
    "title": "嘉陌baby吖"
  },
  {
    "address": "rtmp://xinfusz.zzlsnp.top/live/6007_1754322",
    "img": "http://xingr.biognax.xyz/imgxr/e2b0ce3a36c3dd3d5c.jpg",
    "title": "安遇见你"
  },
  {
    "address": "rtmp://xinfusz.zzlsnp.top/live/6322_1754244",
    "img": "http://xingr.biognax.xyz/imgxr/39e22d48d10fe19870.jpg",
    "title": "寂寞小白白s"
  },
  {
    "address": "http://05ladthe.dianshe.top/live/cx_375008.flv",
    "img": "https://jhgohgfhgfh01.biexd.xyz/7701/live/images/85eaaf2f2ac32560ea2e0957c3b7639c",
    "title": "欧美白人黑人合集"
  },
  {
    "address": "rtmp://xinfusz.zzlsnp.top/live/6924_1754389",
    "img": "http://xingr.biognax.xyz/imgxr/c7a71454211b15a50b.jpg",
    "title": "梨骚妞"
  },
  {
    "address": "http://nchalfjjhgaiarlcxvvflaf.xinzhitushu.xyz/live/cx_379873.flv",
    "img": "https://jhgohgfhgfh01.biexd.xyz/7701/live/images/9e08148e9cc2c030e68e5d296718d230",
    "title": "柒柒56"
  },
  {
    "address": "http://laxghxzaoj.dianshe.top/live/cx_380280.flv",
    "img": "https://jhgohgfhgfh01.biexd.xyz/7701/live/images/68d16e88e3733b824b1eefd3c236d71c",
    "title": "美少女琪琪"
  },
  {
    "address": "http://extlive-pull-ws.inke.cn/live/1754215288421715.flv?auth_version=1&codecInfo=8192&dpSrc=-1&from=hallfe&ikDnsOp=1&ikHost=ws&ikLiveType=multiplayer&ikLog=1&ikNetOp=01111&ikOp=0&md5sum=c42b&pushHost=ext.zego.link.inke.cn&timestamp=1754219080",
    "img": "http://img.ikstatic.cn/MTcyMzk3Njc3MTk5NyMzNTUjanBn.jpg",
    "title": "胖7交友厅"
  },
  {
    "address": "http://001lahoswidx.abrillantlee.top/live/cx_381480.flv",
    "img": "https://jhgohgfhgfh01.biexd.xyz/7701/live/images/beace4073229715cfd8d053749a71a62",
    "title": "念知"
  },
  {
    "address": "http://lamansupasje.abrillantlee.top/live/cx_353436.flv",
    "img": "https://jhgohgfhgfh01.biexd.xyz/7701/live/images/aec0afc3f73098282b334d232b3a9bac",
    "title": "控控"
  },
  {
    "address": "http://01zbiwsadrla.wljzml.top/live/cx_377029.flv",
    "img": "https://jhgohgfhgfh01.biexd.xyz/7701/live/images/e91e69be493909eb3e745c397c79d41c",
    "title": "小孩鱼"
  },
  {
    "address": "http://01lawylahydi.wljzml.top/live/cx_379532.flv",
    "img": "https://jhgohgfhgfh01.biexd.xyz/77lm/live/images/live_img1.jpg",
    "title": "柒萌小玉2"
  },
  {
    "address": "http://mtfvihalkhofnzhftui.xinzhitushu.xyz/live/cx_382779.flv",
    "img": "https://1lozerkusnt.huangyoulin.top/7701/live/images/19f498e4656d2f3c93a682e12e86ceed",
    "title": "想吃奶酪"
  },
  {
    "address": "rtmp://mg0oa.mbubmxok.top/live/5984_1754256",
    "img": "http://mgysals.xavwem.top/imgmg/01353d0d99e7e9519d.jpg",
    "title": "茶茶呀"
  },
  {
    "address": "rtmp://xinfusz.zzlsnp.top/live/6394_1754318",
    "img": "http://xingr.biognax.xyz/imgxr/865cf109305a0efae0.jpg",
    "title": "你滴美"
  },
  {
    "address": "rtmp://xinfusz.zzlsnp.top/live/6975_1754510",
    "img": "http://xingr.biognax.xyz/imgxr/a9894933d1958b39eb.jpg",
    "title": "甜心静静"
  },
  {
    "address": "http://02fahfaola.sturl.top/live/cx_377028.flv",
    "img": "https://jhgohgfhgfh01.biexd.xyz/7701/live/images/9ebd5892ac1246dee8a303287b8aebbf",
    "title": "哈哈梦魔"
  },
  {
    "address": "rtmp://xueli130.vihyvz.top/live/4313_1754606",
    "img": "http://xuelii.tuise.top/images/81ccd4d341f99371da.jpg",
    "title": "第一次做小可爱@"
  },
  {
    "address": "http://extlive-pull-ws.inke.cn/live/1754215288421715.flv?auth_version=1&codecInfo=8192&dpSrc=-1&from=hallfe&ikDnsOp=1&ikHost=ws&ikLiveType=multiplayer&ikLog=1&ikNetOp=01111&ikOp=0&md5sum=a252&pushHost=ext.zego.link.inke.cn&timestamp=1754218899",
    "img": "http://img.ikstatic.cn/MTcyMzk3Njc3MTk5NyMzNTUjanBn.jpg",
    "title": "胖7交友厅"
  }
]